gne_tlidemo/__init__.py
gne_tlidemo/tliDemo.py
gne_tlidemo/templates/demo.html
gne_tlidemo/templates/demoGroupedChart.js
gne_tlidemo/templates/demoPieChart.js
gne_tlidemo/templates/demoScript.html
gne_tlidemo/templates/startStreaming.execute
gne_tlidemo-0.11.dist-info/DESCRIPTION.rst
gne_tlidemo-0.11.dist-info/METADATA
gne_tlidemo-0.11.dist-info/RECORD
gne_tlidemo-0.11.dist-info/WHEEL
gne_tlidemo-0.11.dist-info/metadata.json
gne_tlidemo-0.11.dist-info/top_level.txt
