Metadata-Version: 2.0
Name: gne-tlidemo
Version: 0.11
Summary: Thought Leader Identification Analysis
Home-page: UNKNOWN
Author: IBM Stampede
Author-email: smazumder@us.ibm.com
License: Apache 2.0
Platform: UNKNOWN
Requires-Dist: pixiedust
